chain_aide/__init__.py
chain_aide/contract.py
chain_aide/main.py
chain_aide/utils.py
chain_aide-1.0.5.dist-info/LICENSE
chain_aide-1.0.5.dist-info/METADATA
chain_aide-1.0.5.dist-info/WHEEL
chain_aide-1.0.5.dist-info/top_level.txt
chain_aide-1.0.5.dist-info/RECORD
