Metadata-Version: 2.1
Name: chain-aide
Version: 1.0.5
Summary: An aide that helps you quickly access mainstream public chain and use its basic functions.
Home-page: https://github.com/shinnng/chain-aide
Author: Shinnng
Author-email: shinnng@outlook.com
License: MIT
Keywords: chain
Classifier: Development Status :: 4 - Beta
Classifier: Intended Audience :: Developers
Classifier: License :: OSI Approved :: MIT License
Classifier: Natural Language :: English
Classifier: Programming Language :: Python :: 3
Classifier: Programming Language :: Python :: 3.7
Classifier: Programming Language :: Python :: 3.8
Classifier: Programming Language :: Python :: 3.9
Classifier: Programming Language :: Python :: 3.10
Classifier: Programming Language :: Python :: 3.11
License-File: LICENSE
Requires-Dist: web3 (>=6.0.0)
Requires-Dist: eth-account (>=0.8.0)
Requires-Dist: eth-typing (>=3.3.0)
Requires-Dist: eth-utils (>=2.1.0)
Requires-Dist: loguru (>=0.6.0)
Provides-Extra: chain-aide
Requires-Dist: web3 (>=6.0.0) ; extra == 'chain-aide'
Requires-Dist: eth-account (>=0.8.0) ; extra == 'chain-aide'
Requires-Dist: eth-typing (>=3.3.0) ; extra == 'chain-aide'
Requires-Dist: eth-utils (>=2.1.0) ; extra == 'chain-aide'
Requires-Dist: loguru (>=0.6.0) ; extra == 'chain-aide'
